.gitattributes
AUTHORS
ChangeLog
Introduction to Pycsou.ipynb
LICENSE
README.rst
pycsou.png
requirements-conda.txt
requirements.txt
setup.cfg
setup.py
test.py
doc/conf.py
doc/index.rst
doc/api/index.rst
doc/api/other.rst
doc/api/algorithms/pycsou.opt.proxalgs.rst
doc/api/classes/index.rst
doc/api/classes/pycsou.core.functional.rst
doc/api/classes/pycsou.core.linop.rst
doc/api/classes/pycsou.core.map.rst
doc/api/classes/pycsou.core.solver.rst
doc/api/functionals/index.rst
doc/api/functionals/pycsou.func.base.rst
doc/api/functionals/pycsou.func.loss.rst
doc/api/functionals/pycsou.func.penalty.rst
doc/api/math/index.rst
doc/api/math/pycsou.math.green.rst
doc/api/math/pycsou.math.prox.rst
doc/api/operators/index.rst
doc/api/operators/pycsou.linop.base.rst
doc/api/operators/pycsou.linop.conv.rst
doc/api/operators/pycsou.linop.diff.rst
doc/api/operators/pycsou.linop.sampling.rst
doc/api/utils/pycsou.util.misc.rst
doc/api/utils/pycsou.util.stats.rst
doc/general/examples.rst
doc/general/extensions.rst
doc/general/install.rst
doc/general/pycsou_classes.rst
doc/general/theory.rst
doc/images/Introduction_to_Pycsou_33_1.png
doc/images/IntroductiontoPycsou_38_1.png
doc/images/IntroductiontoPycsou_40_1.png
doc/images/IntroductiontoPycsou_50_1.png
doc/images/IntroductiontoPycsou_53_1.png
doc/images/IntroductiontoPycsou_55_2.png
doc/images/IntroductiontoPycsou_59_2.png
doc/images/IntroductiontoPycsou_62_2.png
doc/images/Pycsou UML.svg
doc/images/Pycsou_UML.png
doc/images/algorithms.png
doc/images/conv_op.png
doc/images/deblurring.jpg
doc/images/diff_op.png
doc/images/image.jpg
doc/images/inpainting.jpg
doc/images/inverse_problem.png
doc/images/lp_cost.png
doc/images/penalty_balls.png
doc/images/penalty_convex.png
doc/images/penalty_div.png
doc/images/penalty_information.png
doc/images/penalty_loss.png
doc/images/penalty_norms.png
doc/images/picsou-png-4.png
doc/images/pixelisation.jpg
doc/images/pooling.jpg
doc/images/pycsou.png
doc/images/samp_op.png
doc/notes/index.rst
pycsou.egg-info/PKG-INFO
pycsou.egg-info/SOURCES.txt
pycsou.egg-info/dependency_links.txt
pycsou.egg-info/pbr.json
pycsou.egg-info/requires.txt
pycsou.egg-info/top_level.txt
pycsou.egg-info/zip-safe
